eventful_aio_pika/__init__.py
eventful_aio_pika/consumer.py
eventful_aio_pika/producer.py
eventful_aio_pika/py.typed
eventful_aio_pika-0.2.1.dist-info/METADATA
eventful_aio_pika-0.2.1.dist-info/WHEEL
eventful_aio_pika-0.2.1.dist-info/RECORD
