Metadata-Version: 2.1
Name: eventful-aio-pika
Version: 0.2.1
Summary: 
Author: niqzart
Author-email: qwert45hi@yandex.ru
Requires-Python: >=3.9,<4.0
Classifier: Programming Language :: Python :: 3
Classifier: Programming Language :: Python :: 3.9
Classifier: Programming Language :: Python :: 3.10
Classifier: Programming Language :: Python :: 3.11
Requires-Dist: aio-pika (>=9.0.5,<10.0.0)
